hangar_matplotlib/__init__.py
hangar_matplotlib/plugin.py
hangar_matplotlib-0.0.3.dist-info/LICENSE
hangar_matplotlib-0.0.3.dist-info/METADATA
hangar_matplotlib-0.0.3.dist-info/WHEEL
hangar_matplotlib-0.0.3.dist-info/entry_points.txt
hangar_matplotlib-0.0.3.dist-info/top_level.txt
hangar_matplotlib-0.0.3.dist-info/RECORD
