Metadata-Version: 2.1
Name: hangar-matplotlib
Version: 0.0.3
Summary: Matplotlib plugin for hangar
Home-page: https://github.com/hhsecond/hangar_matplotlib
Author: hhsecond
Author-email: sherin@tensorwerk.com
License: UNKNOWN
Platform: UNKNOWN
Classifier: Programming Language :: Python :: 3
Classifier: License :: OSI Approved :: Apache Software License
Classifier: Operating System :: OS Independent
Requires-Python: >=3.6
Requires-Dist: matplotlib
